campie/__init__.py
campie/cam.py
campie/kernel.py
campie/py.typed
campie/run.py
campie/types.py
campie/util/__init__.py
campie/util/flip_indices.py
campie/util/helpers.py
campie/validation.py
campie-0.5.0.dist-info/LICENSE
campie-0.5.0.dist-info/METADATA
campie-0.5.0.dist-info/WHEEL
campie-0.5.0.dist-info/entry_points.txt
campie-0.5.0.dist-info/RECORD
