Metadata-Version: 2.1
Name: campie
Version: 0.5.0
Summary: Python APIs to simulate various CAMs on GPUs at scale
Home-page: https://github.com/HewlettPackard/CAMPIE#readme
Requires-Python: >=3.9,<4.0
Classifier: Programming Language :: Python :: 3
Classifier: Programming Language :: Python :: 3.9
Classifier: Programming Language :: Python :: 3.10
Classifier: Programming Language :: Python :: 3.11
Classifier: Programming Language :: Python :: 3.12
Provides-Extra: cu110
Provides-Extra: cu111
Provides-Extra: cu11x
Provides-Extra: cu12x
Requires-Dist: cupy-cuda110 (>=12.3,<13.0) ; extra == "cu110"
Requires-Dist: cupy-cuda111 (>=12.3,<13.0) ; extra == "cu111"
Requires-Dist: cupy-cuda11x (>=13.0,<14.0) ; extra == "cu11x"
Requires-Dist: cupy-cuda12x (>=13.0,<14.0) ; extra == "cu12x"
Requires-Dist: numpy (>=1.26,<2.0)
Project-URL: Repository, https://github.com/HewlettPackard/CAMPIE
